bgpview/__init__.py
bgpview/api_client.py
bgpview/bgpview.py
bgpview/util.py
bgpview_client-0.1.2.dist-info/LICENSE
bgpview_client-0.1.2.dist-info/METADATA
bgpview_client-0.1.2.dist-info/WHEEL
bgpview_client-0.1.2.dist-info/top_level.txt
bgpview_client-0.1.2.dist-info/zip-safe
bgpview_client-0.1.2.dist-info/RECORD
