Metadata-Version: 2.1
Name: bgpview-client
Version: 0.1.2
Summary: bgpview.io api
Home-page: https://github.com/jdhall75/bgpview-client
Author: Jason Hall
Author-email: jdhall75@zohomail.com
License: GNU General Public License v3 (GPLv3)
Keywords: bgpview.io,api,bgp
Classifier: Development Status :: 4 - Beta
Classifier: Topic :: Internet
Classifier: License :: OSI Approved :: GNU General Public License v3 (GPLv3)
Classifier: Programming Language :: Python :: 3.9
Classifier: Programming Language :: Python :: 3.10
Classifier: Programming Language :: Python :: 3.11
License-File: LICENSE
Requires-Dist: requests (>=2.28)
Provides-Extra: dev
Requires-Dist: black ; extra == 'dev'
Requires-Dist: flake8 ; extra == 'dev'
Requires-Dist: typing-extensions ; extra == 'dev'
Requires-Dist: pytest ; extra == 'dev'
Requires-Dist: build ; extra == 'dev'
Requires-Dist: twine ; extra == 'dev'
